static_marks_utils/__init__.py
static_marks_utils/types.py
static_marks_utils-0.1.2.dist-info/METADATA
static_marks_utils-0.1.2.dist-info/WHEEL
static_marks_utils-0.1.2.dist-info/RECORD
