Metadata-Version: 2.1
Name: static-marks-utils
Version: 0.1.2
Summary: Static Marks Utils and Types
Home-page: https://github.com/tddschn/static-marks-utils
License: MIT
Keywords: static-marks
Author: Teddy Xinyuan Chen
Author-email: 45612704+tddschn@users.noreply.github.com
Requires-Python: >=3.12,<4.0
Classifier: License :: OSI Approved :: MIT License
Classifier: Programming Language :: Python :: 3
Classifier: Programming Language :: Python :: 3.12
Classifier: Topic :: Utilities
Project-URL: Bug Tracker, https://github.com/tddschn/static-marks-utils/issues
Project-URL: Repository, https://github.com/tddschn/static-marks-utils
